masgeo/__init__.py
masgeo/common.py
masgeo/masgeo.py
masgeo-0.0.2.dist-info/LICENSE
masgeo-0.0.2.dist-info/METADATA
masgeo-0.0.2.dist-info/WHEEL
masgeo-0.0.2.dist-info/entry_points.txt
masgeo-0.0.2.dist-info/top_level.txt
masgeo-0.0.2.dist-info/RECORD
