Metadata-Version: 2.1
Name: masgeo
Version: 0.0.2
Summary: A python package demo for Mangrove and seagrass identification analysis
Author-email: Carrie Lian <13202920401@163.com>
License: MIT License
Project-URL: Homepage, https://github.com/Ljlgee/masgeo
Keywords: masgeo
Classifier: Intended Audience :: Developers
Classifier: License :: OSI Approved :: MIT License
Classifier: Natural Language :: English
Classifier: Programming Language :: Python :: 3.8
Classifier: Programming Language :: Python :: 3.9
Classifier: Programming Language :: Python :: 3.10
Classifier: Programming Language :: Python :: 3.11
Classifier: Programming Language :: Python :: 3.12
Requires-Python: >=3.8
License-File: LICENSE
Requires-Dist: numpy
Provides-Extra: all
Requires-Dist: masgeo[extra] ; extra == 'all'
Provides-Extra: extra
Requires-Dist: pandas ; extra == 'extra'
